{
  "Aachen": "unexplored",
  "Ahrweiler": "unexplored",
  "Aichach-Friedberg": "unexplored",
  "Alb-Donau-Kreis": "unexplored",
  "Altenburger Land": "unexplored",
  "Altenkirchen": "unexplored",
  "Altmarkkreis Salzwedel": "unexplored",
  "Altötting": "unexplored",
  "Alzey-Worms": "unexplored",
  "Amberg": "unexplored",
  "Amberg-Sulzbach": "unexplored",
  "Ammerland": "unexplored",
  "Anhalt-Bitterfeld": "unexplored",
  "Ansbach": "unexplored",
  "Aschaffenburg": "unexplored",
  "Augsburg": "unexplored",
  "Aurich": "unexplored",
  "Bad Dürkheim": "unexplored",
  "Bad Kissingen": "unexplored",
  "Bad Kreuznach": "unexplored",
  "Bad Tölz-Wolfratshausen": "unexplored",
  "Baden-Baden": "unexplored",
  "Bamberg": "unexplored",
  "Barnim": "unexplored",
  "Bautzen": "unexplored",
  "Bayreuth": "unexplored",
  "Berchtesgadener Land": "unexplored",
  "Bergstraße": "unexplored",
  "Berlin": "unexplored",
  "Bernkastel-Wittlich": "unexplored",
  "Biberach": "unexplored",
  "Bielefeld": "unexplored",
  "Birkenfeld": "unexplored",
  "Bochum": "unexplored",
  "Bodenseekreis": "unexplored",
  "Bonn": "unexplored",
  "Borken": "unexplored",
  "Bottrop": "unexplored",
  "Brandenburg an der Havel": "unexplored",
  "Braunschweig": "unexplored",
  "Breisgau-Hochschwarzwald": "unexplored",
  "Bremen": "unexplored",
  "Bremerhaven": "unexplored",
  "Burgenlandkreis": "unexplored",
  "Böblingen": "unexplored",
  "Börde": "unexplored",
  "Calw": "unexplored",
  "Celle": "unexplored",
  "Cham": "unexplored",
  "Chemnitz": "unexplored",
  "Cloppenburg": "unexplored",
  "Coburg": "unexplored",
  "Cochem-Zell": "unexplored",
  "Coesfeld": "unexplored",
  "Cottbus": "unexplored",
  "Cuxhaven": "unexplored",
  "Dachau": "unexplored",
  "Dahme-Spreewald": "unexplored",
  "Darmstadt": "unexplored",
  "Darmstadt-Dieburg": "unexplored",
  "Deggendorf": "unexplored",
  "Delmenhorst": "unexplored",
  "Dessau-Roßlau": "unexplored",
  "Diepholz": "unexplored",
  "Dillingen": "unexplored",
  "Dingolfing-Landau": "unexplored",
  "Dithmarschen": "unexplored",
  "Donau-Ries": "unexplored",
  "Donnersbergkreis": "unexplored",
  "Dortmund": "unexplored",
  "Dresden": "unexplored",
  "Duisburg": "unexplored",
  "Düren": "unexplored",
  "Düsseldorf": "unexplored",
  "Ebersberg": "unexplored",
  "Eichsfeld": "unexplored",
  "Eichstätt": "unexplored",
  "Eifelkreis Bitburg-Prüm": "unexplored",
  "Eisenach": "unexplored",
  "Elbe-Elster": "unexplored",
  "Emden": "unexplored",
  "Emmendingen": "unexplored",
  "Emsland": "unexplored",
  "Ennepe-Ruhr-Kreis": "unexplored",
  "Enzkreis": "unexplored",
  "Erding": "unexplored",
  "Erfurt": "unexplored",
  "Erlangen": "unexplored",
  "Erlangen-Höchstadt": "unexplored",
  "Erzgebirgskreis": "unexplored",
  "Essen": "unexplored",
  "Esslingen": "unexplored",
  "Euskirchen": "unexplored",
  "Flensburg": "unexplored",
  "Forchheim": "unexplored",
  "Frankenthal": "unexplored",
  "Frankfurt am Main": "unexplored",
  "Frankfurt an der Oder": "unexplored",
  "Freiburg im Breisgau": "unexplored",
  "Freising": "unexplored",
  "Freudenstadt": "unexplored",
  "Freyung-Grafenau": "unexplored",
  "Friesland": "unexplored",
  "Fulda": "unexplored",
  "Fürstenfeldbruck": "unexplored",
  "Fürth": "unexplored",
  "Garmisch-Partenkirchen": "unexplored",
  "Gelsenkirchen": "unexplored",
  "Gera": "unexplored",
  "Germersheim": "unexplored",
  "Gießen": "unexplored",
  "Gifhorn": "unexplored",
  "Goslar": "unexplored",
  "Gotha": "unexplored",
  "Grafschaft Bentheim": "unexplored",
  "Greiz": "unexplored",
  "Groß-Gerau": "unexplored",
  "Göppingen": "unexplored",
  "Görlitz": "unexplored",
  "Göttingen": "unexplored",
  "Günzburg": "unexplored",
  "Gütersloh": "unexplored",
  "Hagen": "unexplored",
  "Halle  Saale ": "unexplored",
  "Hamburg": "unexplored",
  "Hameln-Pyrmont": "unexplored",
  "Hamm": "unexplored",
  "Harburg": "unexplored",
  "Harz": "unexplored",
  "Havelland": "unexplored",
  "Haßberge": "unexplored",
  "Heidekreis": "unexplored",
  "Heidelberg": "unexplored",
  "Heidenheim": "unexplored",
  "Heilbronn": "unexplored",
  "Heinsberg": "unexplored",
  "Helmstedt": "unexplored",
  "Herford": "unexplored",
  "Herne": "unexplored",
  "Hersfeld-Rotenburg": "unexplored",
  "Herzogtum Lauenburg": "unexplored",
  "Hildburghausen": "unexplored",
  "Hildesheim": "unexplored",
  "Hochsauerlandkreis": "unexplored",
  "Hochtaunuskreis": "unexplored",
  "Hof": "unexplored",
  "Hohenlohekreis": "unexplored",
  "Holzminden": "unexplored",
  "Höxter": "unexplored",
  "Ilm-Kreis": "unexplored",
  "Ingolstadt": "unexplored",
  "Jena": "unexplored",
  "Jerichower Land": "unexplored",
  "Kaiserslautern": "unexplored",
  "Karlsruhe": "unexplored",
  "Kassel": "unexplored",
  "Kaufbeuren": "unexplored",
  "Kelheim": "unexplored",
  "Kempten": "unexplored",
  "Kiel": "unexplored",
  "Kitzingen": "unexplored",
  "Kleve": "unexplored",
  "Koblenz": "unexplored",
  "Konstanz": "unexplored",
  "Krefeld": "unexplored",
  "Kronach": "unexplored",
  "Kulmbach": "unexplored",
  "Kusel": "unexplored",
  "Kyffhäuserkreis": "unexplored",
  "Köln": "unexplored",
  "Lahn-Dill-Kreis": "unexplored",
  "Landau in der Pfalz": "unexplored",
  "Landkreis Ansbach": "unexplored",
  "Landkreis Aschaffenburg": "unexplored",
  "Landkreis Augsburg": "unexplored",
  "Landkreis Bamberg": "unexplored",
  "Landkreis Bayreuth": "unexplored",
  "Landkreis Coburg": "unexplored",
  "Landkreis Fürth": "unexplored",
  "Landkreis Heilbronn": "unexplored",
  "Landkreis Hof": "unexplored",
  "Landkreis Kaiserslautern": "unexplored",
  "Landkreis Karlsruhe": "unexplored",
  "Landkreis Kassel": "unexplored",
  "Landkreis Landshut": "unexplored",
  "Landkreis Leipzig": "unexplored",
  "Landkreis Oldenburg": "unexplored",
  "Landkreis Osnabrück": "unexplored",
  "Landkreis Passau": "unexplored",
  "Landkreis Regensburg": "unexplored",
  "Landkreis Rosenheim": "unexplored",
  "Landkreis Rostock": "unexplored",
  "Landkreis Schweinfurt": "unexplored",
  "Landkreis Würzburg": "unexplored",
  "Landsberg am Lech": "unexplored",
  "Landshut": "unexplored",
  "Leer": "unexplored",
  "Leipzig": "unexplored",
  "Leverkusen": "unexplored",
  "Lichtenfels": "unexplored",
  "Limburg-Weilburg": "unexplored",
  "Lindau": "unexplored",
  "Lippe": "unexplored",
  "Ludwigsburg": "unexplored",
  "Ludwigshafen am Rhein": "unexplored",
  "Ludwigslust-Parchim": "unexplored",
  "Lörrach": "unexplored",
  "Lübeck": "unexplored",
  "Lüchow-Dannenberg": "unexplored",
  "Lüneburg": "unexplored",
  "Magdeburg": "unexplored",
  "Main-Kinzig-Kreis": "unexplored",
  "Main-Spessart": "unexplored",
  "Main-Tauber-Kreis": "unexplored",
  "Main-Taunus-Kreis": "unexplored",
  "Mainz": "unexplored",
  "Mainz-Bingen": "unexplored",
  "Mannheim": "unexplored",
  "Mansfeld-Südharz": "unexplored",
  "Marburg-Biedenkopf": "unexplored",
  "Mayen-Koblenz": "unexplored",
  "Mecklenburgische Seenplatte": "unexplored",
  "Meißen": "unexplored",
  "Memmingen": "unexplored",
  "Merzig-Wadern": "unexplored",
  "Mettmann": "unexplored",
  "Miesbach": "unexplored",
  "Miltenberg": "unexplored",
  "Minden-Lübbecke": "unexplored",
  "Mittelsachsen": "unexplored",
  "Munich": "unexplored",
  "Märkisch-Oderland": "unexplored",
  "Märkischer Kreis": "unexplored",
  "Mönchengladbach": "unexplored",
  "Mühldorf": "unexplored",
  "Mülheim an der Ruhr": "unexplored",
  "München": "unexplored",
  "Münster": "unexplored",
  "Neckar-Odenwald-Kreis": "unexplored",
  "Neu-Ulm": "unexplored",
  "Neuburg-Schrobenhausen": "unexplored",
  "Neumarkt": "unexplored",
  "Neumünster": "unexplored",
  "Neunkirchen": "unexplored",
  "Neustadt an der Aisch Bad Windsheim": "unexplored",
  "Neustadt an der Waldnaab": "unexplored",
  "Neustadt an der Weinstraße": "unexplored",
  "Neuwied": "unexplored",
  "Nienburg": "unexplored",
  "Nordfriesland": "unexplored",
  "Nordhausen": "unexplored",
  "Nordsachsen": "unexplored",
  "Nordwestmecklenburg": "unexplored",
  "Northeim": "unexplored",
  "Nürnberg": "unexplored",
  "Nürnberger Land": "unexplored",
  "Oberallgäu": "unexplored",
  "Oberbergischer Kreis": "unexplored",
  "Oberhausen": "unexplored",
  "Oberhavel": "unexplored",
  "Oberspreewald-Lausitz": "unexplored",
  "Odenwaldkreis": "unexplored",
  "Oder-Spree": "unexplored",
  "Offenbach": "unexplored",
  "Offenbach am Main": "unexplored",
  "Oldenburg": "unexplored",
  "Olpe": "unexplored",
  "Ortenaukreis": "unexplored",
  "Osnabrück": "unexplored",
  "Ostalbkreis": "unexplored",
  "Ostallgäu": "unexplored",
  "Osterholz": "unexplored",
  "Ostholstein": "unexplored",
  "Ostprignitz-Ruppin": "unexplored",
  "Paderborn": "unexplored",
  "Passau": "unexplored",
  "Peine": "unexplored",
  "PfaffenHof": "unexplored",
  "Pforzheim": "unexplored",
  "Pinneberg": "unexplored",
  "Pirmasens": "unexplored",
  "Plön": "unexplored",
  "Potsdam": "unexplored",
  "Potsdam-Mittelmark": "unexplored",
  "Prignitz": "unexplored",
  "Rastatt": "unexplored",
  "Ravensburg": "unexplored",
  "Recklinghausen": "unexplored",
  "Regen": "unexplored",
  "Regensburg": "unexplored",
  "Region Hannover": "unexplored",
  "Regionalverband Saarbrücken": "unexplored",
  "Rems-Murr-Kreis": "unexplored",
  "Remscheid": "unexplored",
  "Rendsburg-Eckernförde": "unexplored",
  "Reutlingen": "unexplored",
  "Rhein-Erft-Kreis": "unexplored",
  "Rhein-Hunsrück-Kreis": "unexplored",
  "Rhein-Kreis Neuss": "unexplored",
  "Rhein-Lahn-Kreis": "unexplored",
  "Rhein-Neckar-Kreis": "unexplored",
  "Rhein-Pfalz-Kreis": "unexplored",
  "Rhein-Sieg-Kreis": "unexplored",
  "Rheingau-Taunus-Kreis": "unexplored",
  "Rheinisch-Bergischer Kreis": "unexplored",
  "Rhön-Grabfeld": "unexplored",
  "Rosenheim": "unexplored",
  "Rostock": "unexplored",
  "Rotenburg": "unexplored",
  "Roth": "unexplored",
  "Rottal-Inn": "unexplored",
  "Rottweil": "unexplored",
  "Saale-Holzland-Kreis": "unexplored",
  "Saale-Orla-Kreis": "unexplored",
  "Saalekreis": "unexplored",
  "Saalfeld-Rudolstadt": "unexplored",
  "Saarlouis": "unexplored",
  "Saarpfalz-Kreis": "unexplored",
  "Salzgitter": "unexplored",
  "Salzlandkreis": "unexplored",
  "Schaumburg": "unexplored",
  "Schleswig-Flensburg": "unexplored",
  "Schmalkalden-Meiningen": "unexplored",
  "Schwabach": "unexplored",
  "Schwalm-Eder-Kreis": "unexplored",
  "Schwandorf": "unexplored",
  "Schwarzwald-Baar-Kreis": "unexplored",
  "Schweinfurt": "unexplored",
  "Schwerin": "unexplored",
  "Schwäbisch Hall": "unexplored",
  "Segeberg": "unexplored",
  "Siegen-Wittgenstein": "unexplored",
  "Sigmaringen": "unexplored",
  "Soest": "unexplored",
  "Solingen": "unexplored",
  "Sonneberg": "unexplored",
  "Speyer": "unexplored",
  "Spree-Neiße": "unexplored",
  "St  Wendel": "unexplored",
  "Stade": "unexplored",
  "Starnberg": "unexplored",
  "Steinburg": "unexplored",
  "Steinfurt": "unexplored",
  "Stendal": "unexplored",
  "Stormarn": "unexplored",
  "Straubing": "unexplored",
  "Straubing-Bogen": "unexplored",
  "Stuttgart": "unexplored",
  "Suhl": "unexplored",
  "Sächsische Schweiz-Osterzgebirge": "unexplored",
  "Sömmerda": "unexplored",
  "Südliche Weinstraße": "unexplored",
  "Südwestpfalz": "unexplored",
  "Teltow-Fläming": "unexplored",
  "Tirschenreuth": "unexplored",
  "Traunstein": "unexplored",
  "Trier": "unexplored",
  "Trier-Saarburg": "unexplored",
  "Tuttlingen": "unexplored",
  "Tübingen": "unexplored",
  "Uckermark": "unexplored",
  "Uelzen": "unexplored",
  "Ulm": "unexplored",
  "Unna": "unexplored",
  "Unstrut-Hainich-Kreis": "unexplored",
  "Unterallgäu": "unexplored",
  "Vechta": "unexplored",
  "Verden": "unexplored",
  "Viersen": "unexplored",
  "Vogelsbergkreis": "unexplored",
  "Vogtlandkreis": "unexplored",
  "Vorpommern-Greifswald": "unexplored",
  "Vorpommern-Rügen": "unexplored",
  "Vulkaneifel": "unexplored",
  "Waldeck-Frankenberg": "unexplored",
  "Waldshut": "unexplored",
  "Warendorf": "unexplored",
  "Wartburgkreis": "unexplored",
  "Weiden in der Oberpfalz": "unexplored",
  "Weilheim-Schongau": "unexplored",
  "Weimar": "unexplored",
  "Weimarer Land": "unexplored",
  "Weißenburg-Gunzenhausen": "unexplored",
  "Werra-Meißner-Kreis": "unexplored",
  "Wesel": "unexplored",
  "Wesermarsch": "unexplored",
  "Westerwaldkreis": "unexplored",
  "Wetteraukreis": "unexplored",
  "Wiesbaden": "unexplored",
  "Wilhelmshaven": "unexplored",
  "Wittenberg": "unexplored",
  "Wittmund": "unexplored",
  "Wolfenbüttel": "unexplored",
  "Wolfsburg": "unexplored",
  "Worms": "unexplored",
  "Wunsiedel": "unexplored",
  "Wuppertal": "unexplored",
  "Würzburg": "unexplored",
  "Zollernalbkreis": "unexplored",
  "Zweibrücken": "unexplored",
  "Zwickau": "unexplored"
}